odoo/addons/account_invoice_section_picking/README.rst
odoo/addons/account_invoice_section_picking/__init__.py
odoo/addons/account_invoice_section_picking/__manifest__.py
odoo/addons/account_invoice_section_picking/i18n/account_invoice_section_picking.pot
odoo/addons/account_invoice_section_picking/i18n/es.po
odoo/addons/account_invoice_section_picking/i18n/it.po
odoo/addons/account_invoice_section_picking/models/__init__.py
odoo/addons/account_invoice_section_picking/models/account_move_line.py
odoo/addons/account_invoice_section_picking/models/res_company.py
odoo/addons/account_invoice_section_picking/models/stock_picking.py
odoo/addons/account_invoice_section_picking/readme/CONTRIBUTORS.rst
odoo/addons/account_invoice_section_picking/readme/DESCRIPTION.rst
odoo/addons/account_invoice_section_picking/readme/ROADMAP.rst
odoo/addons/account_invoice_section_picking/static/description/icon.png
odoo/addons/account_invoice_section_picking/static/description/index.html
odoo/addons/account_invoice_section_picking/tests/__init__.py
odoo/addons/account_invoice_section_picking/tests/common.py
odoo/addons/account_invoice_section_picking/tests/test_account_invoice_section_picking.py
odoo/addons/account_invoice_section_picking/tests/test_account_invoice_section_picking_backorder.py
odoo14_addon_account_invoice_section_picking-14.0.1.0.1.dev8.dist-info/METADATA
odoo14_addon_account_invoice_section_picking-14.0.1.0.1.dev8.dist-info/WHEEL
odoo14_addon_account_invoice_section_picking-14.0.1.0.1.dev8.dist-info/top_level.txt
odoo14_addon_account_invoice_section_picking-14.0.1.0.1.dev8.dist-info/RECORD
