Metadata-Version: 2.1
Name: odoo14-addon-account_invoice_section_picking
Version: 14.0.1.0.1.dev8
Summary: Extension of Acccount Invoice Section Sale Order to allow grouping of invoice lines according to delivery picking.
Home-page: https://github.com/OCA/account-invoicing
Author: Camptocamp, Odoo Community Association (OCA)
Author-email: support@odoo-community.org
License: AGPL-3
Classifier: Programming Language :: Python
Classifier: Framework :: Odoo
Classifier: Framework :: Odoo :: 14.0
Classifier: License :: OSI Approved :: GNU Affero General Public License v3
Requires-Python: >=3.6
Requires-Dist: odoo14-addon-account-invoice-section-sale-order
Requires-Dist: odoo<14.1dev,>=14.0a
